MANIFEST.in
README.md
setup.py
bin/install-valkka-core
bin/update-valkka-core
bin/valkka-bionic-install
bin/valkka-kill
bin/valkka-live
bin/valkka-live-generate
bin/valkka-move-ps
bin/valkka-tune
docs/.nojekyll
docs/Makefile
docs/authors.rst
docs/clean.bash
docs/compile.bash
docs/conf.py
docs/faq.rst
docs/fix_rst.py
docs/home.md
docs/index.html
docs/index.rst
docs/intro.rst
docs/license.rst
docs/manual.rst
docs/modules.rst
docs/reinit_docs.bash
docs/requirements.rst
docs/tutorial.save.rst
docs/_build/doctrees/authors.doctree
docs/_build/doctrees/environment.pickle
docs/_build/doctrees/examples.doctree
docs/_build/doctrees/faq.doctree
docs/_build/doctrees/index.doctree
docs/_build/doctrees/intro.doctree
docs/_build/doctrees/license.doctree
docs/_build/doctrees/manual.doctree
docs/_build/doctrees/modules.doctree
docs/_build/doctrees/requirements.doctree
docs/_build/doctrees/submodules.doctree
docs/_build/doctrees/tutorial.doctree
docs/_build/doctrees/tutorial.save.doctree
docs/_build/html/.buildinfo
docs/_build/html/authors.html
docs/_build/html/examples.html
docs/_build/html/faq.html
docs/_build/html/genindex.html
docs/_build/html/index.html
docs/_build/html/intro.html
docs/_build/html/license.html
docs/_build/html/manual.html
docs/_build/html/modules.html
docs/_build/html/objects.inv
docs/_build/html/requirements.html
docs/_build/html/search.html
docs/_build/html/searchindex.js
docs/_build/html/submodules.html
docs/_build/html/tutorial.html
docs/_build/html/tutorial.save.html
docs/_build/html/_downloads/example1.py
docs/_build/html/_downloads/requirements.txt
docs/_build/html/_downloads/86df3b757703bdb72f25c7a8471a46ba/example1.py
docs/_build/html/_downloads/c9079b9b0586c200973a970b6c4da521/example1.py
docs/_build/html/_images/screenshot_1.png
docs/_build/html/_images/skull.png
docs/_build/html/_sources/authors.rst.txt
docs/_build/html/_sources/examples.rst.txt
docs/_build/html/_sources/faq.rst.txt
docs/_build/html/_sources/index.rst.txt
valkka_live.egg-info/PKG-INFO
valkka_live.egg-info/SOURCES.txt
valkka_live.egg-info/dependency_links.txt
valkka_live.egg-info/entry_points.txt
valkka_live.egg-info/requires.txt
valkka_live.egg-info/top_level.txt