Metadata-Version: 2.1
Name: valkka-live
Version: 1.1.1
Summary: Valkka Live video surveillance program
Home-page: https://elsampsa.github.io/valkka-live/
Author: Sampsa Riikonen
Author-email: sampsa.riikonen@iki.fi
License: AGPL
Project-URL: Valkka library, https://elsampsa.github.io/valkka-examples/
Keywords: valkka video surveillance
Platform: UNKNOWN
Classifier: Development Status :: 3 - Alpha
Classifier: Intended Audience :: Developers
Classifier: Operating System :: POSIX :: Linux
Classifier: Topic :: Multimedia :: Video
Classifier: License :: OSI Approved :: GNU Affero General Public License v3 or later (AGPLv3+)
Classifier: Programming Language :: Python :: 3
Provides-Extra: www
